{
  "resourceType": "CodeSystem",
  "status": "draft",
  "content": "complete",
  "name": "PhenotypicFeatureAssertion",
  "id": "phenotypic-feature-assertion",
  "title": "Assertion of Phenotypic Feature Codes",
  "description": "Code System for assertion of phenotypic feature presence",
  "url": "https://nih-ncpi.github.io/ncpi-fhir-ig-2/CodeSystem/phenotypic-feature-assertion",
  "concept": [
    {
      "code": "Present",
      "display": "Present"
    },
    {
      "code": "Absent",
      "display": "Absent"
    },
    {
      "code": "Unknown",
      "display": "Unknown"
    }
  ],
  "experimental": false,
  "caseSensitive": true,
  "count": 3
}
